xinterp-0.1.3.dist-info/METADATA
xinterp-0.1.3.dist-info/WHEEL
xinterp-0.1.3.dist-info/licenses/LICENSE
xinterp.libs/libgcc_s-5b5488a6.so.1
xinterp/__init__.py
xinterp/core.py
xinterp/rust.pypy310-pp73-arm-linux-gnu.so
xinterp-0.1.3.dist-info/RECORD
