Metadata-Version: 2.4
Name: xinterp
Version: 0.1.3
Classifier: Programming Language :: Rust
Classifier: Programming Language :: Python :: Implementation :: CPython
Requires-Dist: numpy
Requires-Dist: black ; extra == 'dev'
Requires-Dist: isort ; extra == 'dev'
Requires-Dist: pytest ; extra == 'dev'
Provides-Extra: dev
License-File: LICENSE
Requires-Python: >=3.8
